deepserializer/__init__.py
deepserializer/serializers.py
deepserializer/views.py
djangorestframework_deepserializer-0.1.17.dist-info/LICENSE
djangorestframework_deepserializer-0.1.17.dist-info/METADATA
djangorestframework_deepserializer-0.1.17.dist-info/WHEEL
djangorestframework_deepserializer-0.1.17.dist-info/top_level.txt
djangorestframework_deepserializer-0.1.17.dist-info/RECORD
