Metadata-Version: 2.1
Name: djangorestframework-deepserializer
Version: 0.1.17
Summary: A package to create deep serializer for django rest framework
Home-page: https://github.com/Horou/djangorestframework-deepserializer
Author: Horou and Enzo_frnt
Keywords: Django,Django REST Framework,Deep,Depth,serializer,viewset,nested,nested serializer
License-File: LICENSE
Requires-Dist: Django
Requires-Dist: djangorestframework
